magicLib/__init__.py
magicLib/magicclass.py
magicLib/magicfunctions.py
magic_lib/__init__.py
magic_lib/magicclass.py
magic_lib/magicfunctions.py
magicfunctions/__init__.py
magicfunctions/myfunctions.py
the_magic_lib-0.1.1.dist-info/METADATA
the_magic_lib-0.1.1.dist-info/WHEEL
the_magic_lib-0.1.1.dist-info/top_level.txt
the_magic_lib-0.1.1.dist-info/RECORD
