Metadata-Version: 2.1
Name: the-magic-lib
Version: 0.1.1
Summary: The magic library
Home-page: https://magic-lib.readthedocs.io/
Author: Louis Nourigeon
License: MIT
Platform: UNKNOWN
